hyou/__init__.py
hyou/client.py
hyou/util.py
hyou-2.1.2.data/scripts/generate_oauth2_credentials.py
hyou-2.1.2.data/scripts/upload_sheet.py
hyou-2.1.2.dist-info/DESCRIPTION.rst
hyou-2.1.2.dist-info/METADATA
hyou-2.1.2.dist-info/RECORD
hyou-2.1.2.dist-info/WHEEL
hyou-2.1.2.dist-info/metadata.json
hyou-2.1.2.dist-info/top_level.txt
