Metadata-Version: 2.0
Name: hyou
Version: 2.1.2
Summary: Pythonic Interface to access Google Spreadsheet
Home-page: https://github.com/google/hyou/
Author: Shuhei Takahashi
Author-email: takahashi.shuhei@gmail.com
License: UNKNOWN
Platform: UNKNOWN
Classifier: Development Status :: 5 - Production/Stable
Classifier: Operating System :: OS Independent
Classifier: Programming Language :: Python :: 2.7
Classifier: License :: OSI Approved :: Apache Software License
Classifier: Topic :: Software Development :: Libraries :: Python Modules
Requires-Dist: gdata (>=2.0.18)
Requires-Dist: google-api-python-client (>=1.6.1)
Requires-Dist: oauth2client (<4.0.0dev,>=1.5.0)
Requires-Dist: pycrypto (>=2.6.1)
Requires-Dist: python-gflags (>=2.0)
